ir_sim-2.9.0.dist-info/licenses/LICENSE
irsim/__init__.py
irsim/version.py
irsim/config/__init__.py
irsim/config/env_param.py
irsim/config/path_param.py
irsim/config/world_param.py
irsim/env/__init__.py
irsim/env/env_base.py
irsim/env/env_base3d.py
irsim/env/env_config.py
irsim/env/env_logger.py
irsim/env/env_plot.py
irsim/env/env_plot3d.py
irsim/gui/__init__.py
irsim/gui/keyboard_control.py
irsim/gui/mouse_control.py
irsim/lib/__init__.py
irsim/lib/algorithm/__init__.py
irsim/lib/algorithm/generation.py
irsim/lib/algorithm/kinematics.py
irsim/lib/algorithm/rvo.py
irsim/lib/behavior/__init__.py
irsim/lib/behavior/behavior.py
irsim/lib/behavior/behavior_methods.py
irsim/lib/behavior/behavior_registry.py
irsim/lib/behavior/group_behavior.py
irsim/lib/behavior/group_behavior_methods.py
irsim/lib/handler/__init__.py
irsim/lib/handler/geometry_handler.py
irsim/lib/handler/kinematics_handler.py
irsim/lib/path_planners/__init__.py
irsim/lib/path_planners/a_star.py
irsim/lib/path_planners/probabilistic_road_map.py
irsim/lib/path_planners/rrt.py
irsim/lib/path_planners/rrt_star.py
irsim/util/__init__.py
irsim/util/random.py
irsim/util/util.py
irsim/world/__init__.py
irsim/world/object_base.py
irsim/world/object_factory.py
irsim/world/object_group.py
irsim/world/world.py
irsim/world/world3d.py
irsim/world/description/car_blue.png
irsim/world/description/car_green.png
irsim/world/description/car_red.png
irsim/world/description/diff_robot0.png
irsim/world/description/diff_robot1.png
irsim/world/map/__init__.py
irsim/world/map/cave.png
irsim/world/map/obstacle_map.py
irsim/world/map/binary_map_generator_hm3d/binary_map_generator.py
irsim/world/map/binary_map_generator_hm3d/hm3d_1.png
irsim/world/map/binary_map_generator_hm3d/hm3d_2.png
irsim/world/map/binary_map_generator_hm3d/hm3d_3.png
irsim/world/map/binary_map_generator_hm3d/hm3d_4.png
irsim/world/map/binary_map_generator_hm3d/hm3d_5.png
irsim/world/map/binary_map_generator_hm3d/hm3d_6.png
irsim/world/map/binary_map_generator_hm3d/hm3d_7.png
ir_sim-2.9.0.dist-info/METADATA
ir_sim-2.9.0.dist-info/WHEEL
ir_sim-2.9.0.dist-info/top_level.txt
ir_sim-2.9.0.dist-info/RECORD
