Metadata-Version: 2.4
Name: ir-sim
Version: 2.9.0
Summary: IR-SIM is an open-source, lightweight robot simulator based on Python, designed for robotics navigation, control, and learning. This simulator provides a simple and user-friendly framework for simulating robots, sensors, and environments, facilitating the development and testing of robotics algorithms with minimal hardware requirements.
Author-email: Han Ruihua <hanrh@connect.hku.hk>
License: MIT License
Project-URL: Homepage, https://ir-sim.readthedocs.io/en/stable/
Project-URL: Documentation, https://ir-sim.readthedocs.io/en/stable/
Project-URL: Repository, https://github.com/hanruihua/ir-sim
Project-URL: Issues, https://github.com/hanruihua/ir-sim/issues
Keywords: robotics,simulation,navigation,control,learning
Classifier: Development Status :: 5 - Production/Stable
Classifier: Topic :: Scientific/Engineering :: Artificial Intelligence
Classifier: Topic :: Software Development :: Libraries :: Python Modules
Classifier: Programming Language :: Python :: 3.9
Classifier: Programming Language :: Python :: 3.10
Classifier: Programming Language :: Python :: 3.11
Classifier: Programming Language :: Python :: 3.12
Classifier: Programming Language :: Python :: 3.13
Classifier: License :: OSI Approved :: MIT License
Classifier: Operating System :: OS Independent
Requires-Python: >=3.9
License-File: LICENSE
Requires-Dist: matplotlib
Requires-Dist: shapely>=2.0.3
Requires-Dist: numpy
Requires-Dist: pyyaml
Requires-Dist: imageio
Requires-Dist: loguru
Requires-Dist: scipy
Provides-Extra: keyboard
Requires-Dist: pynput; extra == "keyboard"
Provides-Extra: all
Requires-Dist: pynput; extra == "all"
Requires-Dist: imageio[ffmpeg]; extra == "all"
Requires-Dist: pyrvo; extra == "all"
Dynamic: license-file
